Fichiers/Artus_de_Chavagnac_task_1/Artus_de_Chavagnac_task_1.vhdl
library IEEE;
use IEEE.STD_LOGIC_1164.ALL;

entity Artus_de_Chavagnac_task_1 is

	Port (

		G0 : in STD_LOGIC;
		G1 : in STD_LOGIC;
		G2 : in STD_LOGIC;

		B0 : out STD_LOGIC;
		B1 : out STD_LOGIC;
		B2 : out STD_LOGIC

		);

end Artus_de_Chavagnac_task_1;

architecture Behavioral of Artus_de_Chavagnac_task_1 is
begin

	condition: process (G0, G1, G2)

		variable vecteur : std_logic_vector (2 downto 0);

	begin

		vecteur := G0 & G1 & G2;

		if vecteur = "000" then

			B0 <= '0';
			B1 <= '0';
			B2 <= '0';

		elsif vecteur = "001" then

			B0 <= '0';
			B1 <= '0';
			B2 <= '1';

		elsif vecteur = "011" then

			B0 <= '0';
			B1 <= '1';
			B2 <= '0';

		elsif vecteur = "010" then

			B0 <= '0';
			B1 <= '1';
			B2 <= '1';

		elsif vecteur = "110" then

			B0 <= '1';
			B1 <= '0';
			B2 <= '0';

		elsif vecteur = "111" then

			B0 <= '1';
			B1 <= '0';
			B2 <= '1';

		elsif vecteur = "101" then

			B0 <= '1';
			B1 <= '1';
			B2 <= '0';

		elsif vecteur = "100" then

			B0 <= '1';
			B1 <= '1';
			B2 <= '1';

		else

			B0 <= 'X';
			B1 <= 'X';
			B2 <= 'X';

		end if;

	end process condition;

end Behavioral;

Fichiers/Artus_de_Chavagnac_task_1/Artus_de_Chavagnac_task_1_tb.vhdl
LIBRARY ieee;
USE ieee.std_logic_1164.ALL;

ENTITY Artus_de_Chavagnac_task_1_tb IS
END Artus_de_Chavagnac_task_1_tb;

ARCHITECTURE behavior OF Artus_de_Chavagnac_task_1_tb IS

COMPONENT Artus_de_Chavagnac_task_1

	PORT(

		G0 : IN STD_LOGIC;
		G1 : IN STD_LOGIC;
		G2 : IN STD_LOGIC;

		B0 : OUT STD_LOGIC;
		B1 : OUT STD_LOGIC;
		B2 : OUT STD_LOGIC

	);

END COMPONENT;

signal G0 : std_logic := '0';
signal G1 : std_logic := '0';
signal G2 : std_logic := '0';

signal B0 : std_logic;
signal B1 : std_logic;
signal B2 : std_logic;

BEGIN

	uut: Artus_de_Chavagnac_task_1 PORT MAP (

		B0 => B0,
		B1 => B1,
		B2 => B2,

		G0 => G0,
		G1 => G1,
		G2 => G2

	);

	stim_proc: process
	begin

		G0 <= '0';
		G1 <= '0';
		G2 <= '0';

		wait for 10 ns;

		G0 <= '0';
		G1 <= '0';
		G2 <= '1';

		wait for 10 ns;
		
		G0 <= '0';
		G1 <= '1';
		G2 <= '1';

		wait for 10 ns;
		
		G0 <= '0';
		G1 <= '1';
		G2 <= '0';

		wait for 10 ns;
		
		G0 <= '1';
		G1 <= '1';
		G2 <= '0';

		wait for 10 ns;
		
		G0 <= '1';
		G1 <= '1';
		G2 <= '1';

		wait for 10 ns;
		
		G0 <= '1';
		G1 <= '0';
		G2 <= '1';

		wait for 10 ns;
		
		G0 <= '1';
		G1 <= '0';
		G2 <= '0';

		wait for 10 ns;

		wait;

	end process;

END;

Fichiers/Artus_de_Chavagnac_task_1/Artus_de_Chavagnac_task_1.vcd
$date
  Fri Nov 18 20:32:15 2022
$end
$version
  GHDL v0
$end
$timescale
  1 fs
$end
$scope module standard $end
$upscope $end
$scope module std_logic_1164 $end
$upscope $end
$scope module artus_de_chavagnac_task_1_tb $end
$var reg 1 ! g0 $end
$var reg 1 " g1 $end
$var reg 1 # g2 $end
$var reg 1 $ b0 $end
$var reg 1 % b1 $end
$var reg 1 & b2 $end
$scope module uut $end
$var reg 1 ' g0 $end
$var reg 1 ( g1 $end
$var reg 1 ) g2 $end
$var reg 1 * b0 $end
$var reg 1 + b1 $end
$var reg 1 , b2 $end
$upscope $end
$upscope $end
$enddefinitions $end
#0
0!
0"
0#
0$
0%
0&
0'
0(
0)
0*
0+
0,
#10000000
1#
1&
1)
1,
#20000000
1"
1%
0&
1(
1+
0,
#30000000
0#
1&
0)
1,
#40000000
1!
1$
0%
0&
1'
1*
0+
0,
#50000000
1#
1&
1)
1,
#60000000
0"
1%
0&
0(
1+
0,
#70000000
0#
1&
0)
1,
