Fichiers/Artus_de_Chavagnac_task_2/Artus_de_Chavagnac_task_2.vhdl
library IEEE;
use IEEE.STD_LOGIC_1164.ALL;
entity Artus_de_Chavagnac_task_2 is
Port (
sens_1 : in STD_LOGIC;
sens_2 : in STD_LOGIC;
sens_3 : in STD_LOGIC;
sens_4 : in STD_LOGIC;
stop : in STD_LOGIC;
turn : out STD_LOGIC;
rotate : out STD_LOGIC
);
end Artus_de_Chavagnac_task_2;
architecture Behavioral of Artus_de_Chavagnac_task_2 is
begin
condition: process (sens_1, sens_2, sens_3, sens_4, stop)
variable vecteur_1 : std_logic_vector (1 downto 0);
variable vecteur_2 : std_logic_vector (1 downto 0);
begin
vecteur_1 := sens_1&sens_2;
vecteur_2 := sens_3&sens_4;
if stop = '1' then
turn <= '0';
rotate <= '0';
else
if vecteur_1 = "00" then
turn <= '1';
elsif vecteur_1 = "11" then
turn <= 'X';
else
turn <= '0';
end if;
if vecteur_2 = "01" then
rotate <= '1';
elsif vecteur_2 = "10" then
rotate <= '0';
else
rotate <= 'X';
end if;
end if;
end process condition;
end Behavioral;

Fichiers/Artus_de_Chavagnac_task_2/Artus_de_Chavagnac_task_2_tb.vhdl
LIBRARY ieee;
USE ieee.std_logic_1164.ALL;
ENTITY Artus_de_Chavagnac_task_2_tb IS
END Artus_de_Chavagnac_task_2_tb;
ARCHITECTURE behavior OF Artus_de_Chavagnac_task_2_tb IS
COMPONENT Artus_de_Chavagnac_task_2
PORT(
sens_1 : IN STD_LOGIC;
sens_2 : IN STD_LOGIC;
sens_3 : IN STD_LOGIC;
sens_4 : IN STD_LOGIC;
stop : IN STD_LOGIC;
turn : OUT STD_LOGIC;
rotate : OUT STD_LOGIC
);
END COMPONENT;
signal sens_1 : std_logic := '0';
signal sens_2 : std_logic := '0';
signal sens_3 : std_logic := '0';
signal sens_4 : std_logic := '0';
signal stop : std_logic := '0';
signal turn : std_logic;
signal rotate : std_logic;
BEGIN
uut: Artus_de_Chavagnac_task_2 PORT MAP (
sens_1 => sens_1,
sens_2 => sens_2,
sens_3 => sens_3,
sens_4 => sens_4,
stop => stop,
turn => turn,
rotate => rotate
);
stim_proc: process
begin
-- part 1: sensors 1 & 2 (stop = 0)
stop <= '0';
sens_1 <= '0';
sens_2 <= '0';
wait for 10 ns;
stop <= '0';
sens_1 <= '0';
sens_2 <= '1';
wait for 10 ns;
stop <= '0';
sens_1 <= '1';
sens_2 <= '0';
wait for 10 ns;
stop <= '0';
sens_1 <= '1';
sens_2 <= '1';
wait for 10 ns;
-- part 2: sensors 3 & 4 (stop = 0), we wait longer than usual to see this separation on the graphs
wait for 20 ns;
stop <= '0';
sens_3 <= '0';
sens_4 <= '0';
wait for 10 ns;
stop <= '0';
sens_3 <= '0';
sens_4 <= '1';
wait for 10 ns;
stop <= '0';
sens_3 <= '1';
sens_4 <= '0';
wait for 10 ns;
stop <= '0';
sens_3 <= '1';
sens_4 <= '1';
wait for 10 ns;
-- part 1: sensors 1 & 2 (stop = 1), we wait longer than usual to see this
separation on the graph
wait for 40 ns;
stop <= '1';
sens_1 <= '0';
sens_2 <= '0';
wait for 10 ns;
stop <= '1';
sens_1 <= '0';
sens_2 <= '1';
wait for 10 ns;
stop <= '1';
sens_1 <= '1';
sens_2 <= '0';
wait for 10 ns;
stop <= '1';
sens_1 <= '1';
sens_2 <= '1';
wait for 10 ns;
-- part 2: sensors 3 & 4 (stop = 1), we wait longer than usual to see this
separation on the graphs
wait for 20 ns;
stop <= '1';
sens_3 <= '0';
sens_4 <= '0';
wait for 10 ns;
stop <= '1';
sens_3 <= '0';
sens_4 <= '1';
wait for 10 ns;
stop <= '1';
sens_3 <= '1';
sens_4 <= '0';
wait for 10 ns;
stop <= '1';
sens_3 <= '1';
sens_4 <= '1';
wait for 10 ns;
wait;
end process;
END;

Fichiers/Artus_de_Chavagnac_task_2/Artus_de_Chavagnac_task_2.vcd
$date
  Wed Nov 09 23:51:50 2022
$end
$version
  GHDL v0
$end
$timescale
  1 fs
$end
$scope module standard $end
$upscope $end
$scope module std_logic_1164 $end
$upscope $end
$scope module artus_de_chavagnac_task_2_tb $end
$var reg 1 ! sens_1 $end
$var reg 1 " sens_2 $end
$var reg 1 # sens_3 $end
$var reg 1 $ sens_4 $end
$var reg 1 % stop $end
$var reg 1 & turn $end
$var reg 1 ' rotate $end
$scope module uut $end
$var reg 1 ( sens_1 $end
$var reg 1 ) sens_2 $end
$var reg 1 * sens_3 $end
$var reg 1 + sens_4 $end
$var reg 1 , stop $end
$var reg 1 - turn $end
$var reg 1 . rotate $end
$upscope $end
$upscope $end
$enddefinitions $end
#0
0!
0"
0#
0$
0%
1&
X'
0(
0)
0*
0+
0,
1-
X.
#10000000
1"
0&
1)
0-
#20000000
1!
0"
1(
0)
#30000000
1"
X&
1)
X-
#40000000
#60000000
#70000000
1$
1'
1+
1.
#80000000
1#
0$
0'
1*
0+
0.
#90000000
1$
X'
1+
X.
#100000000
#140000000
0!
0"
1%
0&
0'
0(
0)
1,
0-
0.
#150000000
1"
1)
#160000000
1!
0"
1(
0)
#170000000
1"
1)
#180000000
#200000000
0#
0$
0*
0+
#210000000
1$
1+
#220000000
1#
0$
1*
0+
#230000000
1$
1+
