Fichiers/BCD_7segments/BCD_7segments.vhdl
library IEEE;
use IEEE.STD_LOGIC_1164.ALL;

entity BCD_7segments is

	Port (

		V1 : in STD_LOGIC;
		V2 : in STD_LOGIC;
		V3 : in STD_LOGIC;
		V4 : in STD_LOGIC;

		a : out STD_LOGIC;
		b : out STD_LOGIC;
		c : out STD_LOGIC;
		d : out STD_LOGIC;
		e : out STD_LOGIC;
		f : out STD_LOGIC;
		g : out STD_LOGIC

	);

end BCD_7segments;

architecture Behavioral of BCD_7segments is
begin

	condition: process (V1, V2, V3, V4)

		variable vecteur : std_logic_vector (3 downto 0);

	begin

		vecteur := V1 & V2 & V3 & V4;

		if vecteur = "0000" then

			a <= '1';
			b <= '1';
			c <= '1';
			d <= '1';
			e <= '1';
			f <= '1';
			g <= '0';

		elsif vecteur = "0001" then

			a <= '0';
			b <= '1';
			c <= '1';
			d <= '0';
			e <= '0';
			f <= '0';
			g <= '0';

		elsif vecteur = "0010" then

			a <= '1';
			b <= '1';
			c <= '0';
			d <= '1';
			e <= '1';
			f <= '0';
			g <= '1';

		elsif vecteur = "0011" then

			a <= '1';
			b <= '1';
			c <= '1';
			d <= '1';
			e <= '0';
			f <= '0';
			g <= '1';

		elsif vecteur = "0100" then

			a <= '0';
			b <= '0';
			c <= '1';
			d <= '0';
			e <= '0';
			f <= '1';
			g <= '1';

		elsif vecteur = "0101" then

			a <= '1';
			b <= '0';
			c <= '1';
			d <= '1';
			e <= '0';
			f <= '1';
			g <= '1';

		elsif vecteur = "0110" then

			a <= '1';
			b <= '0';
			c <= '1';
			d <= '1';
			e <= '1';
			f <= '1';
			g <= '1';

		elsif vecteur = "0111" then

			a <= '1';
			b <= '1';
			c <= '1';
			d <= '0';
			e <= '0';
			f <= '0';
			g <= '0';

		elsif vecteur = "1000" then

			a <= '1';
			b <= '1';
			c <= '1';
			d <= '1';
			e <= '1';
			f <= '1';
			g <= '1';

		elsif vecteur = "1001" then

			a <= '1';
			b <= '1';
			c <= '1';
			d <= '0';
			e <= '0';
			f <= '1';
			g <= '1';

		end if;

	end process condition;

end Behavioral;

Fichiers/BCD_7segments/BCD_7segments_tb.vhdl
LIBRARY ieee;
USE ieee.std_logic_1164.ALL;

ENTITY BCD_7segments_tb IS
END BCD_7segments_tb;

ARCHITECTURE behavior OF BCD_7segments_tb IS

COMPONENT BCD_7segments

	PORT(

		V1 : IN std_logic;
		V2 : IN std_logic;
		V3 : IN std_logic;
		V4 : IN std_logic;

		a : OUT std_logic;
		b : OUT std_logic;
		c : OUT std_logic;
		d : OUT std_logic;
		e : OUT std_logic;
		f : OUT std_logic;
		g : OUT std_logic

	);

END COMPONENT;

signal V1 : std_logic := '0';
signal V2 : std_logic := '0';
signal V3 : std_logic := '0';
signal V4 : std_logic := '0';

signal a : std_logic;
signal b : std_logic;
signal c : std_logic;
signal d : std_logic;
signal e : std_logic;
signal f : std_logic;
signal g : std_logic;

BEGIN

	uut: BCD_7segments PORT MAP (

		V1 => V1,
		V2 => V2,
		V3 => V3,
		V4 => V4,

		a => a,
		b => b,
		c => c,
		d => d,
		e => e,
		f => f,
		g => g

	);

	stim_proc: process
	begin

		wait for 100 ns;

		V1 <= '0';
		V2 <= '0';
		V3 <= '0';
		V4 <= '0';

		wait for 100 ns;

		V1 <= '1';
		V2 <= '0';
		V3 <= '0';
		V4 <= '0';

		wait for 100 ns;

		V1 <= '0';
		V2 <= '1';
		V3 <= '0';
		V4 <= '0';

		wait for 100 ns;
		V1 <= '1';
		V2 <= '1';
		V3 <= '0';
		V4 <= '0';

		wait for 100 ns;

		V1 <= '0';
		V2 <= '0';
		V3 <= '1';
		V4 <= '0';

		wait for 100 ns;

		V1 <= '1';
		V2 <= '0';
		V3 <= '1';
		V4 <= '0';

		wait for 100 ns;

		V1 <= '0';
		V2 <= '1';
		V3 <= '1';
		V4 <= '0';

		wait for 100 ns;

		V1 <= '1';
		V2 <= '1';
		V3 <= '1';
		V4 <= '0';

		wait for 100 ns;

		V1 <= '0';
		V2 <= '0';
		V3 <= '0';
		V4 <= '1';

		wait for 100 ns;

		V1 <= '1';
		V2 <= '0';
		V3 <= '0';
		V4 <= '1';

		wait for 100 ns;

		V1 <= '0';
		V2 <= '0';
		V3 <= '0';
		V4 <= '0';

		wait;

	end process;

END;

Fichiers/BCD_7segments/BCD_7segments.vcd
$date
  Fri Nov 18 20:25:01 2022
$end
$version
  GHDL v0
$end
$timescale
  1 fs
$end
$scope module standard $end
$upscope $end
$scope module std_logic_1164 $end
$upscope $end
$scope module bcd_7segments_tb $end
$var reg 1 ! v1 $end
$var reg 1 " v2 $end
$var reg 1 # v3 $end
$var reg 1 $ v4 $end
$var reg 1 % a $end
$var reg 1 & b $end
$var reg 1 ' c $end
$var reg 1 ( d $end
$var reg 1 ) e $end
$var reg 1 * f $end
$var reg 1 + g $end
$scope module uut $end
$var reg 1 , v1 $end
$var reg 1 - v2 $end
$var reg 1 . v3 $end
$var reg 1 / v4 $end
$var reg 1 0 a $end
$var reg 1 1 b $end
$var reg 1 2 c $end
$var reg 1 3 d $end
$var reg 1 4 e $end
$var reg 1 5 f $end
$var reg 1 6 g $end
$upscope $end
$upscope $end
$enddefinitions $end
#0
0!
0"
0#
0$
1%
1&
1'
1(
1)
1*
0+
0,
0-
0.
0/
10
11
12
13
14
15
06
#100000000
#200000000
1!
1+
1,
16
#300000000
0!
1"
0%
0&
0(
0)
0,
1-
00
01
03
04
#400000000
1!
1,
#500000000
0!
0"
1#
1%
1&
0'
1(
1)
0*
0,
0-
1.
10
11
02
13
14
05
#600000000
1!
1,
#700000000
0!
1"
0&
1'
1*
0,
1-
01
12
15
#800000000
1!
1,
#900000000
0!
0"
0#
1$
0%
1&
0(
0)
0*
0+
0,
0-
0.
1/
00
11
03
04
05
06
#1000000000
1!
1%
1*
1+
1,
10
15
16
#1100000000
0!
0$
1(
1)
0+
0,
0/
13
14
06
