Fichiers/task_1/task_1.vhdl
library IEEE;
use IEEE.STD_LOGIC_1164.ALL;

entity task_1 is

	Port (

		B0 : in STD_LOGIC;
		B1 : in STD_LOGIC;
		B2 : in STD_LOGIC;

		G0 : out STD_LOGIC;
		G1 : out STD_LOGIC;
		G2 : out STD_LOGIC

		);

end task_1;

architecture Behavioral of task_1 is
begin

	condition: process (B0, B1, B2)

		variable vecteur : std_logic_vector (2 downto 0);

	begin

		vecteur := B0 & B1 & B2;

		if vecteur = "000" then

			G0 <= '0';
			G1 <= '0';
			G2 <= '0';

		elsif vecteur = "001" then

			G0 <= '0';
			G1 <= '0';
			G2 <= '1';

		elsif vecteur = "010" then

			G0 <= '0';
			G1 <= '1';
			G2 <= '1';

		elsif vecteur = "011" then

			G0 <= '0';
			G1 <= '1';
			G2 <= '0';

		elsif vecteur = "100" then

			G0 <= '1';
			G1 <= '1';
			G2 <= '0';

		elsif vecteur = "101" then

			G0 <= '1';
			G1 <= '1';
			G2 <= '1';

		elsif vecteur = "110" then

			G0 <= '1';
			G1 <= '0';
			G2 <= '1';

		elsif vecteur = "111" then

			G0 <= '1';
			G1 <= '0';
			G2 <= '0';

		else

			G0 <= 'X';
			G1 <= 'X';
			G2 <= 'X';

		end if;

	end process condition;

end Behavioral;

Fichiers/task_1/task_1_tb.vhdl
LIBRARY ieee;
USE ieee.std_logic_1164.ALL;

ENTITY task_1_tb IS
END task_1_tb;

ARCHITECTURE behavior OF task_1_tb IS

COMPONENT task_1

	PORT(

		B0 : IN STD_LOGIC;
		B1 : IN STD_LOGIC;
		B2 : IN STD_LOGIC;

		G0 : OUT STD_LOGIC;
		G1 : OUT STD_LOGIC;
		G2 : OUT STD_LOGIC

		);

END COMPONENT;

signal B0 : std_logic := '0';
signal B1 : std_logic := '0';
signal B2 : std_logic := '0';

signal G0 : std_logic;
signal G1 : std_logic;
signal G2 : std_logic;

BEGIN

	uut: task_1 PORT MAP (

		B0 => B0,
		B1 => B1,
		B2 => B2,

		G0 => G0,
		G1 => G1,
		G2 => G2

	);

	stim_proc: process
	begin

		B0 <= '0';
		B1 <= '0';
		B2 <= '0';

		wait for 10 ns;

		B0 <= '0';
		B1 <= '0';
		B2 <= '1';

		wait for 10 ns;
		
		B0 <= '0';
		B1 <= '1';
		B2 <= '0';

		wait for 10 ns;
		
		B0 <= '0';
		B1 <= '1';
		B2 <= '1';

		wait for 10 ns;
		
		B0 <= '1';
		B1 <= '0';
		B2 <= '0';

		wait for 10 ns;
		
		B0 <= '1';
		B1 <= '0';
		B2 <= '1';

		wait for 10 ns;
		
		B0 <= '1';
		B1 <= '1';
		B2 <= '0';

		wait for 10 ns;
		
		B0 <= '1';
		B1 <= '1';
		B2 <= '1';

		wait for 10 ns;

		wait;

	end process;

END;

Fichiers/task_1/task_1.vcd
$date
  Fri Nov 18 20:33:31 2022
$end
$version
  GHDL v0
$end
$timescale
  1 fs
$end
$scope module standard $end
$upscope $end
$scope module std_logic_1164 $end
$upscope $end
$scope module task_1_tb $end
$var reg 1 ! b0 $end
$var reg 1 " b1 $end
$var reg 1 # b2 $end
$var reg 1 $ g0 $end
$var reg 1 % g1 $end
$var reg 1 & g2 $end
$scope module uut $end
$var reg 1 ' b0 $end
$var reg 1 ( b1 $end
$var reg 1 ) b2 $end
$var reg 1 * g0 $end
$var reg 1 + g1 $end
$var reg 1 , g2 $end
$upscope $end
$upscope $end
$enddefinitions $end
#0
0!
0"
0#
0$
0%
0&
0'
0(
0)
0*
0+
0,
#10000000
1#
1&
1)
1,
#20000000
1"
0#
1%
1(
0)
1+
#30000000
1#
0&
1)
0,
#40000000
1!
0"
0#
1$
1'
0(
0)
1*
#50000000
1#
1&
1)
1,
#60000000
1"
0#
0%
1(
0)
0+
#70000000
1#
0&
1)
0,
