Fichiers/full_adder/full_adder.vhdl
library IEEE;
use IEEE.STD_LOGIC_1164.ALL;

entity full_adder is

	Port (

		a : in STD_LOGIC;
		b : in STD_LOGIC;
		cin : in STD_LOGIC;

		s : out STD_LOGIC;
		cout : out STD_LOGIC

	);

end full_adder;

architecture Behavioral of full_adder is
begin

	s <= (a xor b) xor cin;
	cout <= (a and b) or (a and cin) or (b and cin);

end Behavioral;

Fichiers/full_adder/full_adder_tb.vhdl
LIBRARY ieee;
USE ieee.std_logic_1164.ALL;

ENTITY full_adder_tb IS
END full_adder_tb;

ARCHITECTURE behavior OF full_adder_tb IS

COMPONENT full_adder

	PORT(

		a : IN std_logic;
		b : IN std_logic;
		cin : IN std_logic;

		s : OUT std_logic;
		cout : OUT std_logic

	);

END COMPONENT;

signal a : std_logic := '0';
signal b : std_logic := '0';
signal cin : std_logic := '0';

signal s : std_logic;
signal cout : std_logic;

BEGIN

	uut: full_adder PORT MAP (

		a => a,
		b => b,
		cin => cin,

		s => s,
		cout => cout

	);

	stim_proc: process
	begin

		a <= '0';
		b <= '0';
		cin <= '0';

		wait for 10 ns;

		a <= '1';
		b <= '0';
		cin <= '0';

		wait for 10 ns;

		a <= '0';
		b <= '1';
		cin <= '0';

		wait for 10 ns;

		a <= '1';
		b <= '1';
		cin <= '0';

		wait for 10 ns;

		a <= '0';
		b <= '0';
		cin <= '1';

		wait for 10 ns;

		a <= '1';
		b <= '0';
		cin <= '1';

		wait for 10 ns;

		a <= '0';
		b <= '1';
		cin <= '1';

		wait for 10 ns;

		a <= '1';
		b <= '1';
		cin <= '1';

		wait for 10 ns;

		wait;

	end process;

END;

Fichiers/full_adder/full_adder.vcd
$date
  Fri Nov 18 16:40:44 2022
$end
$version
  GHDL v0
$end
$timescale
  1 fs
$end
$scope module standard $end
$upscope $end
$scope module std_logic_1164 $end
$upscope $end
$scope module full_adder_tb $end
$var reg 1 ! a $end
$var reg 1 " b $end
$var reg 1 # cin $end
$var reg 1 $ s $end
$var reg 1 % cout $end
$scope module uut $end
$var reg 1 & a $end
$var reg 1 ' b $end
$var reg 1 ( cin $end
$var reg 1 ) s $end
$var reg 1 * cout $end
$upscope $end
$upscope $end
$enddefinitions $end
#0
0!
0"
0#
0$
0%
0&
0'
0(
0)
0*
#10000000
1!
1$
1&
1)
#20000000
0!
1"
0&
1'
#30000000
1!
0$
1%
1&
0)
1*
#40000000
0!
0"
1#
1$
0%
0&
0'
1(
1)
0*
#50000000
1!
0$
1%
1&
0)
1*
#60000000
0!
1"
0&
1'
#70000000
1!
1$
1&
1)
